rotalabs_comply/__init__.py
rotalabs_comply/_version.py
rotalabs_comply/audit/__init__.py
rotalabs_comply/audit/encryption.py
rotalabs_comply/audit/logger.py
rotalabs_comply/audit/storage.py
rotalabs_comply/core/__init__.py
rotalabs_comply/core/config.py
rotalabs_comply/core/exceptions.py
rotalabs_comply/core/types.py
rotalabs_comply/frameworks/__init__.py
rotalabs_comply/frameworks/base.py
rotalabs_comply/frameworks/eu_ai_act.py
rotalabs_comply/frameworks/gdpr.py
rotalabs_comply/frameworks/hipaa.py
rotalabs_comply/frameworks/iso_42001.py
rotalabs_comply/frameworks/mas.py
rotalabs_comply/frameworks/nist_ai_rmf.py
rotalabs_comply/frameworks/soc2.py
rotalabs_comply/reports/__init__.py
rotalabs_comply/reports/generator.py
rotalabs_comply/reports/templates.py
rotalabs_comply/utils/__init__.py
rotalabs_comply/utils/helpers.py
rotalabs_comply-1.0.0.dist-info/METADATA
rotalabs_comply-1.0.0.dist-info/WHEEL
rotalabs_comply-1.0.0.dist-info/licenses/LICENSE
rotalabs_comply-1.0.0.dist-info/RECORD
